<?xml version="1.0" encoding="utf-8"?>
<!DOCTYPE hibernate-mapping PUBLIC "-//Hibernate/Hibernate Mapping DTD 3.0//EN"
"http://www.hibernate.org/dtd/hibernate-mapping-3.0.dtd ">
<!-- 
    Mapping file autogenerated by MyEclipse Persistence Tools
-->
<hibernate-mapping>
    <class name="ppms.domain.OperatorNj" table="operator_nj" schema="PANDAUSER">
        <id name="operatorId" type="java.lang.Integer">
            <column name="OperatorId" precision="8" scale="0" />
            <generator class="assigned" />
        </id>
        <many-to-one name="organizationNj" class="ppms.domain.OrganizationNj" fetch="select">
            <column name="OrgId" precision="8" scale="0" />
        </many-to-one>
        <property name="name" type="java.lang.String">
            <column name="Name" length="160" />
        </property>
        <property name="sex" type="java.lang.Boolean">
            <column name="Sex" precision="1" scale="0" />
        </property>
        <property name="addr" type="java.lang.String">
            <column name="Addr" length="256" />
        </property>
        <property name="telephone" type="java.lang.String">
            <column name="Telephone" length="40" />
        </property>
        <property name="office" type="java.lang.String">
            <column name="Office" length="256" />
        </property>
        <property name="createTime" type="java.util.Date">
            <column name="CreateTime" length="7" />
        </property>
        <property name="invalidTime" type="java.util.Date">
            <column name="InvalidTime" length="7" />
        </property>
        <property name="statusId" type="java.lang.Boolean">
            <column name="StatusId" precision="1" scale="0" />
        </property>
        <property name="maxLoginTimes" type="java.lang.Byte">
            <column name="MaxLoginTimes" precision="2" scale="0" />
        </property>
        <property name="currLoginTimes" type="java.lang.Byte">
            <column name="CurrLoginTimes" precision="2" scale="0" />
        </property>
        <property name="empNo" type="java.lang.Integer">
            <column name="EmpNo" precision="8" scale="0" />
        </property>
        <property name="type" type="java.lang.Boolean">
            <column name="Type" precision="1" scale="0" />
        </property>
        <property name="mobile" type="java.lang.String">
            <column name="Mobile" length="40" />
        </property>
        <property name="changeDate" type="java.util.Date">
            <column name="ChangeDate" length="7" />
        </property>
    </class>
</hibernate-mapping>
