<?xml version="1.0" encoding="utf-8"?>
<!DOCTYPE hibernate-mapping PUBLIC "-//Hibernate/Hibernate Mapping DTD 3.0//EN"
"http://www.hibernate.org/dtd/hibernate-mapping-3.0.dtd ">
<!-- 
    Mapping file autogenerated by MyEclipse Persistence Tools
-->
<hibernate-mapping>
    <class name="ppms.domain.TbPost" table="tb_Post" schema="PANDAUSER">
        <id name="postId" type="java.lang.String">
            <column name="PostId" length="6" />
            <generator class="assigned" />
        </id>
        <property name="postName" type="java.lang.String">
            <column name="PostName" length="20" />
        </property>
        <property name="postComment" type="java.lang.String">
            <column name="PostComment" length="200" />
        </property>
        <property name="seq" type="java.lang.String">
            <column name="Seq" length="2" />
        </property>
        <property name="createdBy" type="java.lang.String">
            <column name="CreatedBy" length="6" />
        </property>
        <property name="createdTime" type="java.util.Date">
            <column name="CreatedTime" length="7" />
        </property>
        <property name="modifiedBy" type="java.lang.String">
            <column name="ModifiedBy" length="6" />
        </property>
        <property name="modifiedTime" type="java.util.Date">
            <column name="ModifiedTime" length="7" />
        </property>
        <property name="deletedTime" type="java.util.Date">
            <column name="DeletedTime" length="7" />
        </property>
        <set name="tbEmployees" inverse="true">
            <key>
                <column name="PostId" length="6" />
            </key>
            <one-to-many class="ppms.domain.TbEmployee" />
        </set>
        <set name="tbJobs" inverse="true">
            <key>
                <column name="PostId" length="6" />
            </key>
            <one-to-many class="ppms.domain.TbJob" />
        </set>
    </class>
</hibernate-mapping>
